vrp_quantum_solver/__init__.py
vrp_quantum_solver/model/StepVRP.py
vrp_quantum_solver/model/VRP.py
vrp_quantum_solver/model/VRPSolution.py
vrp_quantum_solver/model/dispatcher.py
vrp_quantum_solver/model/adapter/Adapter.py
vrp_quantum_solver/model/adapter/DWaveAdapter.py
vrp_quantum_solver/model/adapter/QiskitAdapter.py
vrp_quantum_solver/model/cvrp/ConstantCVRP.py
vrp_quantum_solver/model/cvrp/InfiniteCVRP.py
vrp_quantum_solver/model/cvrp/MultiCVRP.py
vrp_quantum_solver/model/rpp/CapacityRPP.py
vrp_quantum_solver/model/rpp/InfiniteRPP.py
vrp_quantum_solver/qiskit_algorithms/.editorconfig
vrp_quantum_solver/qiskit_algorithms/.git-blame-ignore-revs
vrp_quantum_solver/qiskit_algorithms/.gitignore
vrp_quantum_solver/qiskit_algorithms/.mailmap
vrp_quantum_solver/qiskit_algorithms/.mergify.yml
vrp_quantum_solver/qiskit_algorithms/.pylintdict
vrp_quantum_solver/qiskit_algorithms/.stestr.conf
vrp_quantum_solver/qiskit_algorithms/CODE_OF_CONDUCT.md
vrp_quantum_solver/qiskit_algorithms/CONTRIBUTING.md
vrp_quantum_solver/qiskit_algorithms/LICENSE.txt
vrp_quantum_solver/qiskit_algorithms/MANIFEST.in
vrp_quantum_solver/qiskit_algorithms/Makefile
vrp_quantum_solver/qiskit_algorithms/README.md
vrp_quantum_solver/qiskit_algorithms/constraints.txt
vrp_quantum_solver/qiskit_algorithms/mypy.ini
vrp_quantum_solver/qiskit_algorithms/pyproject.toml
vrp_quantum_solver/qiskit_algorithms/requirements-dev.txt
vrp_quantum_solver/qiskit_algorithms/requirements.txt
vrp_quantum_solver/qiskit_algorithms/setup.py
vrp_quantum_solver/qiskit_algorithms/tox.ini
vrp_quantum_solver/qiskit_algorithms/.github/CODEOWNERS
vrp_quantum_solver/qiskit_algorithms/.github/PULL_REQUEST_TEMPLATE.md
vrp_quantum_solver/qiskit_algorithms/.github/dependabot.yml
vrp_quantum_solver/qiskit_algorithms/.github/ISSUE_TEMPLATE/BUG_REPORT.yaml
vrp_quantum_solver/qiskit_algorithms/.github/ISSUE_TEMPLATE/FEATURE_REQUEST.yaml
vrp_quantum_solver/qiskit_algorithms/.github/actions/install-algorithms/action.yml
vrp_quantum_solver-1.0.2.dist-info/METADATA
vrp_quantum_solver-1.0.2.dist-info/WHEEL
vrp_quantum_solver-1.0.2.dist-info/licenses/LICENSE
vrp_quantum_solver-1.0.2.dist-info/RECORD
