Metadata-Version: 2.3
Name: vrp-quantum-solver
Version: 1.0.2
Summary: Package to solve vehicle routing problems using quantum optimization algorithms
Project-URL: Homepage, https://github.com/BrunoRosendo/vrp-quantum-solver
Project-URL: Issues, https://github.com/BrunoRosendo/vrp-quantum-solver/issues
Project-URL: Thesis, https://hdl.handle.net/10216/160532
Author-email: Bruno Rosendo <brunomrosendo@hotmail.com>
License-File: LICENSE
Classifier: License :: OSI Approved :: MIT License
Classifier: Operating System :: OS Independent
Classifier: Programming Language :: Python :: 3
Requires-Python: >=3.8
Requires-Dist: dimod>=0.12.14
Requires-Dist: docplex>=2.25.236
Requires-Dist: dwave-system>=1.23.0
Requires-Dist: numpy>=1.23.5
Requires-Dist: ortools>=9.10.4067
Requires-Dist: plotly>=5.19.0
Requires-Dist: qiskit-ibm-runtime==0.23.0
Requires-Dist: qiskit-optimization>=0.6.1
Requires-Dist: qiskit-optimization[cplex]
Requires-Dist: qiskit==1.0.2
Provides-Extra: dev
Requires-Dist: ddt!=1.4.0,!=1.4.3,>=1.2.0; extra == 'dev'
Requires-Dist: pyenchant>=3.2.2; extra == 'dev'
Requires-Dist: rustworkx>=0.13; extra == 'dev'
